CHANGELOG.md
LICENSE
MANIFEST.in
README.md
requirements.txt
setup.py
amplremote/__init__.py
amplremote/auth.py
amplremote/client.py
amplremote/jobs.py
amplremote/server.py
amplremote/swagger.yml
amplremote/worker.py
amplremote.egg-info/PKG-INFO
amplremote.egg-info/SOURCES.txt
amplremote.egg-info/dependency_links.txt
amplremote.egg-info/requires.txt
amplremote.egg-info/top_level.txt
scripts/amplserver
scripts/amplserver.bat
scripts/remote
scripts/remote.bat